[
  {
    "id": "event-1",
    "translations": {
      "en": {
        "title": "Electronic Euphoria",
        "description": "Progressive house and techno night with international DJs"
      },
      "ru": {
        "title": "Электронная Эйфория",
        "description": "Прогрессив хаус и техно ночь с международными диджеями"
      },
      "he": {
        "title": "אופוריה אלקטרונית",
        "description": "לילה של פרוגרסיב האוס וטכנו עם תקליטנים בינלאומיים"
      }
    },
    "date": "2024-04-15",
    "time": "22:00",
    "type": "party",
    "price": 80,
    "image": "/assets/ui/backgrounds/about/disco/492231185_1243597314437632_4946434647322291015_n.jpg",
    "bookingUrl": "https://example.com/book/1",
    "featured": true
  },
  {
    "id": "event-2",
    "translations": {
      "en": {
        "title": "Live Jazz Sessions",
        "description": "Intimate jazz performances with local and international artists"
      },
      "ru": {
        "title": "Джазовые Сессии",
        "description": "Камерные джазовые выступления с местными и международными артистами"
      },
      "he": {
        "title": "מופעי ג'אז חיים",
        "description": "הופעות ג'אז אינטימיות עם אמנים מקומיים ובינלאומיים"
      }
    },
    "date": "2024-04-18",
    "time": "21:00",
    "type": "live",
    "price": 60,
    "image": "/assets/ui/backgrounds/about/live-concerts/513951011_1300841258713237_3364042759429850319_n.jpg",
    "bookingUrl": "https://example.com/book/2",
    "featured": true
  },
  {
    "id": "event-3",
    "translations": {
      "en": {
        "title": "Comedy Night",
        "description": "Stand-up comedy with the best local comedians"
      },
      "ru": {
        "title": "Вечер Комедии",
        "description": "Стендап комедия с лучшими местными комиками"
      },
      "he": {
        "title": "ערב סטנדאפ",
        "description": "מופעי סטנדאפ עם מיטב הקומיקאים המקומיים"
      }
    },
    "date": "2024-04-20",
    "time": "20:00",
    "type": "standup",
    "price": 0,
    "image": "/assets/ui/backgrounds/about/standup/500280366_1271018098362220_8295739600963142980_n.jpg",
    "bookingUrl": "https://example.com/book/3"
  }
]
